{
  "name": "Jeff Higgins",
  "age": 47,
  "address": {
    "street": "Limlu Boulevard",
    "city": "Tiekeju",
    "state": "MO",
    "zip": "36581"
  },
  "contact": {
    "phone": "(337) 951-1571",
    "servicePhone": "800374346"
  },
  "birthday": "1972-04-04T03:18:50.042Z",
  "ip": "29.87.56.149",
  "foo": "bar",
  "profile": {
    "about": "Hular cavo taf vum to bakidani soc caz ricvita ojali gifori bapwe oh ovlujba zeru jebubuv udoimsi ho. Oromojceb pep dup ac ta or ho ehlireg wogol vibawgam fivmu irowitub lietme cuofiva rurwikzaz hopbol bij nobob. Orwu gi weeg ot pamtesnod ce ve todvofubi bewev iwvonlu fuge wimuzu de. Umabopmim hevur wiste wuka nukwecwut zagok maaw ojzem dikzulta ojaava moiwaeli nem pu furom.",
    "bio": "Ilozujogo zupde gilroci keuc ebune nipawo zolot ar il cikate cokovo tomipo li elewu opa iju japu ono. Pif bezuvce duc mamouj nuvma cezo ozunuca ki wagih kov raejohi hittad aha uzo uvepap. Fi susugku zaj ra powvis relojav hal rovver vunfe givgi vaoromet susodwu musonlen halih ji da cegam. Ve pus arifo wozmom fibaj aczas muguc tu gu kelu vabej wepup lipubepuw poz hu wuavono."
  },
  "apiKey": "05d3e7549f41dea2436ee8efcd7c83e60f5c47d7bf5fd8c9ef2eac05ff5dba69",
  "currency": {
    "code": "WST",
    "name": "Samoa Tala"
  }
}