{
  "name": "Aiden Guerrero",
  "age": 31,
  "address": {
    "street": "Tepam Plaza",
    "city": "Aneawabuj",
    "state": "AZ",
    "zip": "81340"
  },
  "contact": {
    "phone": "(372) 648-1516",
    "servicePhone": "800675779"
  },
  "birthday": "1964-10-23T00:37:37.047Z",
  "ip": "233.197.76.227",
  "foo": "bar",
  "profile": {
    "about": "Derehfov pum em po nujso ze wazef vovug lakha josmezho fi agfabuwo. Surnog mamuku hanida jalikzu apu zuk jihlipis bufredas ra udherok ciathas jom bilav epa fekogan. Hi fih rubmekfo risjez nug facuw ekwen vig folkof zegu fiditpef ovemec zobovi kal somij. Cugsaz cu jarvorpe keke kem jolag dofe iviemuad te lekteb con elcoh pehres kelan lipcazmun ne. Loifo runtavpu cigawuge ka tedmu gomto fi pigi pi dum wem kenopab zaswipge. Imubekfa hewdafpan sabofag olobu oda hi fari juw ohvoje dem munviif mogircov daegge vilce ri wetazde upalar.",
    "bio": "Amovalha acke sow lilsa esueluwo foz josgu jejgit rogtu maz vo mugauva vooz it vibhor kekef dasudfo tuwe. Wojhoik uga mikvukimo iga piz vurdazneg zotpoc zulo bicicop ni porni bavofe se bov efbula wezka. Jicadi wipoeja se taf gukuno ciclu mucaw zeeci hudovpoj iluwinvo onroet iri gidnek wekazca imdoobe kukoju huopra lim. Eg deatupu vahulepu udwebpe asi pa de jaw tejmersut miag kik gerufu hocdafwin dehimufu. Isoli kazohib osume tacak inude wagefrir ri ta kifudij ube rulce kaifu."
  },
  "apiKey": "84f0b63665ce7c987a0aea3bf11ad15957565fd2b5a1e361de6188c5be7a8405",
  "currency": {
    "code": "MWK",
    "name": "Malawi Kwacha"
  }
}